Bidirectional Buffer/Bidirectional.v
module Bidirectional (
    A,B,en
);
    inout A,B;
    input en;
    assign A = (en)?1'bz:B;
    assign B = (en)?A:1'bz;
endmodule

Bidirectional Buffer/Bidirectional_tb.v
module Bidirectional_tb();
    integer en_int,A_int,B_int;
    reg en;
    reg In_A,In_B; // These regesters will drive the A and B
    wire A,B;
    Bidirectional Bi(A,B,en);
    
    assign A = en?In_A:1'bz;
    assign B = ~en?In_B:1'bz;

    initial begin
        for (en_int =0 ;en_int<2 ;en_int=en_int+1 ) begin
            en = en_int;
            for (A_int =0 ;A_int<2 ;A_int = A_int+1 ) begin
                In_A = A_int;
                for (B_int = 0;B_int<2 ;B_int = B_int+1 ) begin
                    In_B = B_int;
                    #5;
                end
            end
        end
    end
    
    initial begin
        $dumpfile("Bidirectional_tb.vcd");
        $dumpvars(0,Bidirectional_tb);

        $monitor($time,"A = %b, Enable = %b, B = %b", A,en,B);
        #200 $finish;   
    end
endmodule

Bidirectional Buffer/Bidirectional_tb.vcd
$date
	Tue Feb 08 23:26:06 2022
$end
$version
	ModelSim Version 2020.1
$end
$timescale
	1ps
$end

$scope module Bidirectional_tb $end
$var integer 32 ! en_int $end
$var integer 32 " A_int $end
$var integer 32 # B_int $end
$var reg 1 $ en $end
$var reg 1 % In_A $end
$var reg 1 & In_B $end
$var wire 1 ' A $end
$var wire 1 ( B $end

$scope module Bi $end
$var wire 1 ' A $end
$var wire 1 ( B $end
$var wire 1 ) en $end
$upscope $end
$upscope $end
$enddefinitions $end
#0
$dumpvars
0$
0%
0&
b0 !
b0 "
b0 #
0'
0(
0)
$end
#5
b1 #
1&
1(
1'
#10
b10 #
b1 "
1%
b0 #
0&
0(
0'
#15
b1 #
1&
1(
1'
#20
b10 #
b10 "
b1 !
1$
b0 "
0%
b0 #
0&
x'
z(
0'
1)
0(
#25
b1 #
1&
#30
b10 #
b1 "
1%
b0 #
0&
1'
1(
#35
b1 #
1&
#40
b10 #
b10 "
b10 !
